pyson_connect/__init__.py
pyson_connect/errors.py
pyson_connect/pyson_connect.py
pyson_connect-0.2.42.dist-info/LICENSE
pyson_connect-0.2.42.dist-info/METADATA
pyson_connect-0.2.42.dist-info/WHEEL
pyson_connect-0.2.42.dist-info/top_level.txt
pyson_connect-0.2.42.dist-info/RECORD
