Metadata-Version: 2.1
Name: pyson-connect
Version: 0.2.42
Summary: pyson_connect: This is the third party module for using a Epson Connect
Home-page: https://github.com/clipper-programing/pyson_connect
Author: Ryuse Sato(inchoxd)
Author-email: incho@clpr.pro
License: UNKNOWN
Platform: UNKNOWN
Classifier: Programming Language :: Python :: 3.8
Classifier: License :: OSI Approved :: BSD License
Classifier: Operating System :: OS Independent
Requires-Python: >=3.6
Requires-Dist: requests (>=2.25.1)
Requires-Dist: Pillow (>=8.0.1)
